zenbroker/__init__.py
zenbroker/client.py
zenbroker/test.py
zenbroker-1.5.2.dist-info/METADATA
zenbroker-1.5.2.dist-info/WHEEL
zenbroker-1.5.2.dist-info/top_level.txt
zenbroker-1.5.2.dist-info/RECORD
