Metadata-Version: 2.1
Name: zenbroker
Version: 1.5.2
Summary: Zenbroker client
Home-page: UNKNOWN
License: UNKNOWN
Platform: UNKNOWN
Requires-Dist: pydantic<3.0.0,>=2.0.0
Requires-Dist: httpx<1.0.0,>=0.28.0
Requires-Dist: python-socketio<6.0.0,>=5.0.0
Requires-Dist: websocket-client<2.0.0,>=1.8.0
